setup.py
django_spoolgore.egg-info/PKG-INFO
django_spoolgore.egg-info/SOURCES.txt
django_spoolgore.egg-info/dependency_links.txt
django_spoolgore.egg-info/top_level.txt
spoolgore/__init__.py
spoolgore/backend.py