Metadata-Version: 1.0
Name: django-spoolgore
Version: 0.1
Summary: A django EMAIL_BACKEND for enqueuing mail in the Spoolgore daemon.
Home-page: https://github.com/20tab/django-spoolgore
Author: 20Tab S.r.l.
Author-email: info@20tab.com
License: UNKNOWN
Platform: UNKNOWN
